MANIFEST.in
README.md
setup.py
netssh/__init__.py
netssh/navigation.py
netssh/urls.py
netssh/views.py
netssh.egg-info/PKG-INFO
netssh.egg-info/SOURCES.txt
netssh.egg-info/dependency_links.txt
netssh.egg-info/top_level.txt
netssh/static/netssh/css/bootstrap.min.css
netssh/static/netssh/css/fullscreen.min.css
netssh/static/netssh/css/xterm.min.css
netssh/static/netssh/css/fonts/.gitignore
netssh/static/netssh/img/favicon.png
netssh/static/netssh/js/bootstrap.min.js
netssh/static/netssh/js/jquery.min.js
netssh/static/netssh/js/main.js
netssh/static/netssh/js/popper.min.js
netssh/static/netssh/js/xterm-addon-fit.min.js
netssh/static/netssh/js/xterm.min.js
netssh/templates/netssh/home.html
netssh/templates/netssh/index.html
netssh/templates/netssh/static/css/bootstrap.min.css
netssh/templates/netssh/static/css/fullscreen.min.css
netssh/templates/netssh/static/css/xterm.min.css
netssh/templates/netssh/static/css/fonts/.gitignore
netssh/templates/netssh/static/img/favicon.png
netssh/templates/netssh/static/js/bootstrap.min.js
netssh/templates/netssh/static/js/jquery.min.js
netssh/templates/netssh/static/js/main.js
netssh/templates/netssh/static/js/popper.min.js
netssh/templates/netssh/static/js/xterm-addon-fit.min.js
netssh/templates/netssh/static/js/xterm.min.js